{
  "data": {
    "getCaregiver": {
      "continuousBackgroundCheck": {
        "seeker": {
          "hasLimitReached": false,
          "subscriptionStatus": null,
          "__typename": "SeekerContinuousBgcSubscriptionDto"
        },
        "hasActiveHit": false,
        "__typename": "ContinuousBackgroundCheck"
      },
      "backgroundChecks": [
        {
          "backgroundCheckName": "CARE_CHECK",
          "whenCompleted": "2024-09-24T03:28:00.000Z",
          "__typename": "BackgroundCheck"
        }
      ],
      "badges": [
        "BACKGROUND_CHECK",
        "VACCINATED"
      ],
      "distanceFromSeekerInMiles": null,
      "educationDegrees": [
        {
          "currentlyAttending": false,
          "degreeYear": null,
          "educationLevel": "COLLEGE_DEGREE",
          "schoolName": "",
          "educationDetailsText": [
            "College degree"
          ],
          "__typename": "EducationDegree"
        }
      ],
      "hasCareCheck": true,
      "hasGrantedCriminalBGCAccess": false,
      "hasGrantedMvrBGCAccess": false,
      "hasGrantedPremierBGCAccess": false,
      "hiredByCounts": {
        "locality": null,
        "__typename": "CaregiverHiredByCounts"
      },
      "hiredTimes": 0,
      "isFavorite": false,
      "isMVREligible": true,
      "isVaccinated": true,
      "member": {
        "id": "3107714f-a7cf-4435-a857-63158ae6fc1a",
        "lastName": "W",
        "firstName": "Cramlita",
        "gender": "FEMALE",
        "hiResImageURL": "https://www.care.com/s/d/aws/photo/1080X1080/78/46302878_hlzo9iWQDdg6CbzdjPP6KINTIGmx010",
        "displayName": "Cramlita W.",
        "email": "frihaouiayoube@gmail.com",
        "primaryService": "SENIOR_CARE",
        "imageURL": "https://www.care.com/s/d/aws/photo/135X135/78/46302878_hlzo9iWQDdg6CbzdjPP6KINTIGmx010",
        "address": {
          "city": "Decatur",
          "state": "GA",
          "zip": "30035",
          "__typename": "Address"
        },
        "languages": [
          "ENGLISH"
        ],
        "legacyId": "60341592",
        "isPremium": false,
        "__typename": "Member"
      },
      "placeInfo": null,
      "profiles": {
        "serviceIds": [
          "HOUSEKEEPING",
          "SENIOR_CARE"
        ],
        "childCareCaregiverProfile": null,
        "commonCaregiverProfile": {
          "id": "",
          "repeatClientsCount": 0,
          "merchandizedJobInterests": {
            "companionCare": true,
            "dateNight": false,
            "lightCleaning": true,
            "mealPrepLaundry": true,
            "mover": false,
            "personalAssistant": true,
            "petHelp": false,
            "shopping": true,
            "transportation": true,
            "__typename": "MerchandizedJobInterests"
          },
          "__typename": "CommonCaregiverProfile"
        },
        "petCareCaregiverProfile": null,
        "seniorCareCaregiverProfile": {
          "approvalStatus": "APPROVED",
          "availabilityFrequency": "FULL_TIME",
          "bio": {
            "experienceSummary": "My name is Cramlita. I have 6 years of caregiver experience, certified Cna, and 2 years of housekeeping experience. I am CPR certified. I enjoy meeting new people, making their lives a little easier, and taking care of their loved ones. I believe you should treat people how you want to be treated. I look forward to meeting you all",
            "title": null,
            "__typename": "Bio"
          },
          "id": "32972241",
          "otherQualities": [],
          "payRange": {
            "hourlyRateFrom": {
              "amount": "18",
              "currencyCode": "USD",
              "__typename": "Money"
            },
            "hourlyRateTo": {
              "amount": "18",
              "currencyCode": "USD",
              "__typename": "Money"
            },
            "__typename": "PayRange"
          },
          "qualities": {
            "alzheimersOrDementiaExperience": true,
            "certifiedNursingAssistant": true,
            "comfortableWithPets": false,
            "cprTrained": true,
            "doesNotSmoke": true,
            "firstAidTraining": false,
            "homeHealthAideExperience": false,
            "hospiceExperience": true,
            "licensedNurse": false,
            "medicalEquipmentExperience": false,
            "ownTransportation": true,
            "registeredNurse": false,
            "woundCare": false,
            "__typename": "SeniorCareCaregiverQualities"
          },
          "recurringRate": {
            "hourlyRateFrom": {
              "currencyCode": "USD",
              "amount": "18",
              "__typename": "Money"
            },
            "hourlyRateTo": {
              "currencyCode": "USD",
              "amount": "18",
              "__typename": "Money"
            },
            "__typename": "PayRange"
          },
          "supportedServices": {
            "visitingPhysician": false,
            "visitingNurse": false,
            "transportation": true,
            "specializedCare": true,
            "specialNeeds": false,
            "respiteCare": false,
            "personalCare": true,
            "mobilityAssistance": true,
            "medicalTransportation": false,
            "medicalManagement": false,
            "mealPreparation": true,
            "lightHousekeeping": true,
            "liveInHomeCare": false,
            "hospiceServices": true,
            "homeModification": false,
            "homeHealth": false,
            "helpStayingPhysicallyActive": false,
            "heavyLifting": false,
            "feeding": true,
            "errands": true,
            "dementia": true,
            "companionship": true,
            "bathing": true,
            "__typename": "SeniorCareCaregiverServices"
          },
          "yearsOfExperience": 7,
          "__typename": "SeniorCareCaregiverProfile"
        },
        "tutoringCaregiverProfile": null,
        "houseKeepingCaregiverProfile": {
          "approvalStatus": "APPROVED",
          "availabilityFrequency": "FULL_TIME",
          "bio": {
            "experienceSummary": "My name is Cramlita. I have 6 years of caregiver experience and 2 years of housekeeping experience. I am CPR certified. I have three children 18, 15, and 8. I enjoy meeting new people, making their lives a little easier, and taking care of their loved ones. I believe you should treat people how you want to be treated. I look forward to meeting you all",
            "title": null,
            "__typename": "Bio"
          },
          "distanceWillingToTravel": null,
          "id": "32994086",
          "otherQualities": [],
          "payRange": {
            "hourlyRateFrom": {
              "amount": "16",
              "currencyCode": "USD",
              "__typename": "Money"
            },
            "hourlyRateTo": {
              "amount": "21",
              "currencyCode": "USD",
              "__typename": "Money"
            },
            "__typename": "PayRange"
          },
          "qualities": {
            "comfortableWithPets": false,
            "doesNotSmoke": true,
            "ownTransportation": true,
            "providesEquipment": false,
            "providesSupplies": false,
            "__typename": "HousekeeperQualities"
          },
          "recurringRate": {
            "hourlyRateFrom": {
              "amount": "16",
              "currencyCode": "USD",
              "__typename": "Money"
            },
            "hourlyRateTo": {
              "amount": "21",
              "currencyCode": "USD",
              "__typename": "Money"
            },
            "__typename": "PayRange"
          },
          "schedule": [],
          "supportedServices": {
            "atticCleaning": false,
            "basementCleaning": false,
            "bathroomCleaning": true,
            "cabinetCleaning": false,
            "carpetCleaning": false,
            "changingBedLinens": true,
            "deepCleaning": false,
            "dishes": false,
            "dusting": false,
            "furnitureTreatment": false,
            "generalRoomCleaning": true,
            "houseSitting": false,
            "kitchenCleaning": false,
            "laundry": true,
            "moveOutCleaning": false,
            "organization": false,
            "ovenCleaning": false,
            "packingUnpacking": false,
            "petWasteCleanup": false,
            "plantCare": false,
            "refrigeratorCleaning": false,
            "standardCleaning": false,
            "surfacePolishing": false,
            "vacuumingOrMopping": false,
            "wallWashing": false,
            "windowWashing": false,
            "__typename": "HousekeeperServices"
          },
          "yearsOfExperience": 3,
          "__typename": "HouseKeepingCaregiverProfile"
        },
        "__typename": "CaregiverProfiles"
      },
      "providerStatus": "ACTIVE",
      "recurringAvailability": {
        "dayList": {
          "monday": {
            "blocks": [
              {
                "end": "16:00:00",
                "start": "08:00:00",
                "__typename": "LocalTimeBlock"
              }
            ],
            "__typename": "DailySchedule"
          },
          "tuesday": {
            "blocks": [
              {
                "end": "16:00:00",
                "start": "08:00:00",
                "__typename": "LocalTimeBlock"
              }
            ],
            "__typename": "DailySchedule"
          },
          "wednesday": {
            "blocks": [
              {
                "end": "16:00:00",
                "start": "08:00:00",
                "__typename": "LocalTimeBlock"
              }
            ],
            "__typename": "DailySchedule"
          },
          "thursday": {
            "blocks": [
              {
                "end": "16:30:00",
                "start": "08:00:00",
                "__typename": "LocalTimeBlock"
              }
            ],
            "__typename": "DailySchedule"
          },
          "friday": {
            "blocks": [
              {
                "end": "16:00:00",
                "start": "08:00:00",
                "__typename": "LocalTimeBlock"
              }
            ],
            "__typename": "DailySchedule"
          },
          "saturday": {
            "blocks": [],
            "__typename": "DailySchedule"
          },
          "sunday": {
            "blocks": [],
            "__typename": "DailySchedule"
          },
          "__typename": "WeeklySchedule"
        },
        "__typename": "RecurringAvailability"
      },
      "responseRate": 0,
      "responseTime": 0,
      "signUpDate": "2023-08-10T01:25:00.000Z",
      "yearsOfExperience": 0,
      "nonPrimaryImages": [
        "https://www.care.com/s/d/aws/photo/1080X1080/11/45988411_hlzo9iWQDdg6CbzdjPP6KINTIGmx010"
      ],
      "__typename": "Caregiver"
    }
  }
}