{
  "data": {
    "reviewsByReviewee": {
      "__typename": "ReviewsByRevieweePayload",
      "nextPageToken": "",
      "reviews": [
        {
          "attributes": [
            {
              "truthy": true,
              "type": "REHIRED",
              "__typename": "ReviewInfoAttribute"
            }
          ],
          "careType": "HOUSEKEEPING",
          "createTime": "2022-03-31T15:46:15.000Z",
          "deleteTime": null,
          "description": {
            "displayText": "Haydee is wonderful! Reliable, takes initiative, open to feedback and implements it well. She has a positive attitude and is very conscientious. I highly recommend working with her!",
            "originalText": "Haydee is wonderful! Reliable, takes initiative, open to feedback and implements it well. She has a positive attitude and is very conscientious. I highly recommend working with her!",
            "__typename": "ReviewInfoText"
          },
          "id": "c64aef4b-b6f8-41cd-bea2-6b75c6b1785a",
          "languageCode": "en-us",
          "originalSource": "CZEN",
          "ratings": [
            {
              "type": "OVERALL",
              "value": 5,
              "__typename": "ReviewInfoRating"
            },
            {
              "type": "DEPENDABILITY",
              "value": 5,
              "__typename": "ReviewInfoRating"
            },
            {
              "type": "PUNCTUALITY",
              "value": 5,
              "__typename": "ReviewInfoRating"
            }
          ],
          "retort": null,
          "reviewee": {
            "id": "7abc554b-e15f-483d-b644-db297428536b",
            "providerType": "INDIVIDUAL",
            "type": "PROVIDER",
            "__typename": "ReviewInfoReviewee"
          },
          "reviewer": {
            "imageURL": "https://www.care.com/s/d/aws/photo/135X135/20/41426020_l4RC3bgAcRAUAwhkV2xbYVpFAc6Xkl00",
            "publicMemberInfo": {
              "firstName": "Yael",
              "lastInitial": "S",
              "__typename": "PublicMemberInfo"
            },
            "source": "CZEN",
            "type": "SEEKER",
            "__typename": "ReviewInfoReviewer"
          },
          "status": "APPROVED",
          "updateSource": "CZEN",
          "updateTime": "2022-04-03T10:43:36.000Z",
          "verifiedByCare": false,
          "__typename": "ReviewInfo"
        }
      ]
    }
  }
}