{
    "id": 8959913,
    "verticalId": "childCare",
    "displayName": "Elena R.",
    "firstName": "Elena",
    "memberType": "individual",
    "summary": "J' ai gardé des enfants dès mes 16 ans  de tout âge j' ai également fait de l'accompagnement scolaire et encadré des enfants lors de séjours linguistiques. J' ai aussi été professeur de langues pour des élèves de la 3 ème à la terminale en espagnol et anglais. Je suis à la recherche de garde d enfants soit en soirée soit les weekends.",
    "hourlyRate": 10,
    "yearsOfExperience": 10,
    "daysSinceLastLogin": 116,
    "premiumStatus": "basic",
    "location": "Paris",
    "rating": {
        "total": 0
    },
    "memberSince": "2024-11-20T09:23Z",
    "age": 56,
    "bookmarked": false,
    "reviewed": false,
    "ableToReview": false,
    "currencySymbol": "",
    "qualifications": [],
    "documents": [],
    "links": [
        {
            "href": "https://www.care.com/fr-fr/reportMember/show?reportedMemberId=227c150e-dac3-4081-8af5-ab2afe3d72b3&contentType=Profile",
            "rel": "report",
            "type": "GET"
        },
        {
            "href": "https://www.care.com/fr-fr/my-account/message/17168370?verticalProfile=8959913",
            "rel": "thread",
            "type": "GET"
        },
        {
            "href": "https://www.care.com/fr-fr/api/v1/profile-bookmarks",
            "rel": "bookmark",
            "type": "POST",
            "data": [
                {
                    "key": "encryptedProfileId",
                    "value": "ZWtYQ1BqeWNhdFpGb1prZkgwdlh6QT09"
                }
            ]
        },
        {
            "href": "https://www.care.com/fr-fr/api/v1/profile-bookmarks?encryptedProfileId=ZWtYQ1BqeWNhdFpGb1prZkgwdlh6QT09",
            "rel": "deleteBookmark",
            "type": "DELETE"
        },
        {
            "href": "https://www.care.com/fr-fr/my-account/billing/upgrade?profileId=8959913",
            "rel": "upgrade",
            "type": "GET"
        }
    ],
    "verifications": [
        {
            "verifiedItem": "phone",
            "verified": false
        },
        {
            "verifiedItem": "email",
            "verified": false
        }
    ],
    "aboutDetails": [
        "nonSmoker",
        "comfortableWithPets"
    ],
    "highlights": [],
    "services": {
        "childCareServices": [
            "swimmingSupervision",
            "pickupDropoff",
            "cookingMealPrep",
            "lightHouseKeeping",
            "bathing",
            "virtualCare",
            "availableForAfterschoolCare",
            "bringingBed"
        ]
    },
    "experience": {
        "childCareExperience": [
            "earlySchool",
            "toddler",
            "preteenOrTeen",
            "primarySchool",
            "two"
        ]
    },
    "icebreakerQuestions": [
        {
            "key": "providerProfilePageReact.questions.childCare.availability",
            "links": [
                {
                    "href": "https://www.care.com/fr-fr/my-account/question",
                    "rel": "sendQuestion",
                    "type": "POST",
                    "data": [
                        {
                            "key": "providerId",
                            "value": "17168370"
                        },
                        {
                            "key": "code",
                            "value": "providerProfile.questions.childCare.availability"
                        },
                        {
                            "key": "verticalId",
                            "value": "childCare"
                        }
                    ]
                },
                {
                    "href": "https://www.care.com/fr-fr/event/questionEvent",
                    "rel": "sendQuestionEvent",
                    "type": "POST",
                    "data": [
                        {
                            "key": "providerId",
                            "value": "17168370"
                        },
                        {
                            "key": "profileId",
                            "value": "8959913"
                        },
                        {
                            "key": "question",
                            "value": "providerProfile.questions.childCare.availability"
                        },
                        {
                            "key": "vertical",
                            "value": "childCare"
                        }
                    ]
                }
            ]
        },
        {
            "key": "providerProfilePageReact.questions.childCare.experience",
            "links": [
                {
                    "href": "https://www.care.com/fr-fr/my-account/question",
                    "rel": "sendQuestion",
                    "type": "POST",
                    "data": [
                        {
                            "key": "providerId",
                            "value": "17168370"
                        },
                        {
                            "key": "code",
                            "value": "providerProfile.questions.childCare.experience"
                        },
                        {
                            "key": "verticalId",
                            "value": "childCare"
                        }
                    ]
                },
                {
                    "href": "https://www.care.com/fr-fr/event/questionEvent",
                    "rel": "sendQuestionEvent",
                    "type": "POST",
                    "data": [
                        {
                            "key": "providerId",
                            "value": "17168370"
                        },
                        {
                            "key": "profileId",
                            "value": "8959913"
                        },
                        {
                            "key": "question",
                            "value": "providerProfile.questions.childCare.experience"
                        },
                        {
                            "key": "vertical",
                            "value": "childCare"
                        }
                    ]
                }
            ]
        },
        {
            "key": "providerProfilePageReact.questions.childCare.compatibility",
            "links": [
                {
                    "href": "https://www.care.com/fr-fr/my-account/question",
                    "rel": "sendQuestion",
                    "type": "POST",
                    "data": [
                        {
                            "key": "providerId",
                            "value": "17168370"
                        },
                        {
                            "key": "code",
                            "value": "providerProfile.questions.childCare.compatibility"
                        },
                        {
                            "key": "verticalId",
                            "value": "childCare"
                        }
                    ]
                },
                {
                    "href": "https://www.care.com/fr-fr/event/questionEvent",
                    "rel": "sendQuestionEvent",
                    "type": "POST",
                    "data": [
                        {
                            "key": "providerId",
                            "value": "17168370"
                        },
                        {
                            "key": "profileId",
                            "value": "8959913"
                        },
                        {
                            "key": "question",
                            "value": "providerProfile.questions.childCare.compatibility"
                        },
                        {
                            "key": "vertical",
                            "value": "childCare"
                        }
                    ]
                }
            ]
        }
    ]
}