{
  "data": {
    "getCaregiver": {
      "continuousBackgroundCheck": {
        "seeker": {
          "hasLimitReached": false,
          "subscriptionStatus": null,
          "__typename": "SeekerContinuousBgcSubscriptionDto"
        },
        "hasActiveHit": false,
        "__typename": "ContinuousBackgroundCheck"
      },
      "backgroundChecks": [
        {
          "backgroundCheckName": "CARE_CHECK",
          "whenCompleted": "2024-12-17T11:25:00.000Z",
          "__typename": "BackgroundCheck"
        }
      ],
      "badges": [
        "BACKGROUND_CHECK"
      ],
      "distanceFromSeekerInMiles": null,
      "educationDegrees": [
        {
          "currentlyAttending": true,
          "degreeYear": null,
          "educationLevel": "SOME_COLLEGE",
          "schoolName": "Hudson County Community College",
          "educationDetailsText": [
            "Hudson County Community College",
            "Currently attending",
            "Some college"
          ],
          "__typename": "EducationDegree"
        }
      ],
      "hasCareCheck": true,
      "hasGrantedCriminalBGCAccess": false,
      "hasGrantedMvrBGCAccess": false,
      "hasGrantedPremierBGCAccess": false,
      "hiredByCounts": {
        "locality": null,
        "__typename": "CaregiverHiredByCounts"
      },
      "hiredTimes": 7,
      "isFavorite": false,
      "isMVREligible": true,
      "isVaccinated": false,
      "member": {
        "id": "7016da29-9175-43aa-acf3-55d4b029a839",
        "lastName": "K",
        "firstName": "Marina",
        "gender": "FEMALE",
        "hiResImageURL": "https://www.care.com/s/d/aws/photo/1080X1080/62/45639462_TZqzRERvf4QzTNDq7W01UeIdtfrdt00",
        "displayName": "Marina K.",
        "email": "frihaouiayoube@gmail.com",
        "primaryService": "CHILD_CARE",
        "imageURL": "https://www.care.com/s/d/aws/photo/135X135/62/45639462_TZqzRERvf4QzTNDq7W01UeIdtfrdt00",
        "address": {
          "city": "Bayonne",
          "state": "NJ",
          "zip": "07002",
          "__typename": "Address"
        },
        "languages": [
          "ARABIC",
          "ENGLISH"
        ],
        "legacyId": "52775735",
        "isPremium": false,
        "__typename": "Member"
      },
      "placeInfo": null,
      "profiles": {
        "serviceIds": [
          "CHILD_CARE",
          "PET_CARE"
        ],
        "childCareCaregiverProfile": {
          "approvalStatus": "APPROVED",
          "ageGroups": [
            "NEWBORN",
            "TODDLER",
            "EARLY_SCHOOL",
            "ELEMENTARY_SCHOOL",
            "TEEN"
          ],
          "availabilityFrequency": "PART_TIME",
          "bio": {
            "experienceSummary": "My name is Marina, I'm a collage student studying early childhood education. I would say I'm a very calm and patient person. Im also very caring when it comes to a child's need. I grew up taking care of my baby cousins while their parents are at work and whenever they needed assistance in the house. I have worked with ages 4 months- 4 years old. I'm great with kids and kind. I don't raise my voice or yell I'm very understanding when a kid is upset and do my best to calm them down and cheer them up when upset. I have been babysitting for 3 years now on the app and met a lot of great families.",
            "title": null,
            "aiAssistedBio": false,
            "__typename": "Bio"
          },
          "childStaffRatio": null,
          "id": "29710207",
          "maxAgeMonths": null,
          "minAgeMonths": null,
          "numberOfChildren": 1,
          "offerings": null,
          "otherQualities": [],
          "payRange": {
            "hourlyRateFrom": {
              "amount": "18",
              "currencyCode": "USD",
              "__typename": "Money"
            },
            "hourlyRateTo": {
              "amount": "19",
              "currencyCode": "USD",
              "__typename": "Money"
            },
            "__typename": "PayRange"
          },
          "qualities": {
            "afterSchoolCare": false,
            "babysitter": true,
            "certifiedNursingAssistant": false,
            "certifiedRegisterNurse": false,
            "certifiedTeacher": false,
            "childDevelopmentAssociate": false,
            "comfortableWithPets": true,
            "cprTrained": false,
            "crn": false,
            "doesNotSmoke": true,
            "doula": false,
            "earlyChildDevelopmentCoursework": false,
            "earlyChildhoodEducation": true,
            "firstAidTraining": false,
            "mothersHelper": false,
            "nafccCertified": false,
            "nanny": true,
            "newbornCareSpecialist": false,
            "nightNanny": false,
            "ownTransportation": false,
            "specialNeedsCare": false,
            "trustlineCertifiedCalifornia": false,
            "__typename": "ChildCareCaregiverQualities"
          },
          "recurringRate": {
            "hourlyRateFrom": {
              "amount": "18",
              "__typename": "Money"
            },
            "hourlyRateTo": {
              "amount": "19",
              "__typename": "Money"
            },
            "__typename": "PayRange"
          },
          "rates": [
            {
              "hourlyRate": {
                "amount": "28",
                "currencyCode": "USD",
                "__typename": "Money"
              },
              "numberOfChildren": 1,
              "isDefaulted": true,
              "__typename": "OneTimeChildCareRates"
            }
          ],
          "supportedServices": {
            "carpooling": false,
            "craftAssistance": false,
            "errands": false,
            "groceryShopping": false,
            "laundryAssistance": false,
            "lightHousekeeping": true,
            "mealPreparation": true,
            "swimmingSupervision": false,
            "travel": false,
            "__typename": "ChildCareCaregiverServices"
          },
          "yearsOfExperience": 3,
          "__typename": "ChildCareCaregiverProfile"
        },
        "commonCaregiverProfile": {
          "id": "29710207",
          "repeatClientsCount": 0,
          "merchandizedJobInterests": {
            "companionCare": true,
            "dateNight": true,
            "lightCleaning": true,
            "mealPrepLaundry": true,
            "mover": true,
            "personalAssistant": true,
            "petHelp": true,
            "shopping": true,
            "transportation": true,
            "__typename": "MerchandizedJobInterests"
          },
          "__typename": "CommonCaregiverProfile"
        },
        "petCareCaregiverProfile": {
          "approvalStatus": "APPROVED",
          "rates": [
            {
              "activity": "Sitting",
              "activityRate": {
                "amount": "45",
                "currencyCode": "USD",
                "__typename": "Money"
              },
              "activityRateUnit": "night",
              "__typename": "OneTimePetCareRates"
            },
            {
              "activity": "Boarding",
              "activityRate": {
                "amount": "41",
                "currencyCode": "USD",
                "__typename": "Money"
              },
              "activityRateUnit": "night",
              "__typename": "OneTimePetCareRates"
            },
            {
              "activity": "Doggy day care",
              "activityRate": {
                "amount": "41",
                "currencyCode": "USD",
                "__typename": "Money"
              },
              "activityRateUnit": "day",
              "__typename": "OneTimePetCareRates"
            },
            {
              "activity": "30-minute dog walk",
              "activityRate": {
                "amount": "18",
                "currencyCode": "USD",
                "__typename": "Money"
              },
              "activityRateUnit": "walk",
              "__typename": "OneTimePetCareRates"
            },
            {
              "activity": "60-minute dog walk",
              "activityRate": {
                "amount": "28",
                "currencyCode": "USD",
                "__typename": "Money"
              },
              "activityRateUnit": "walk",
              "__typename": "OneTimePetCareRates"
            }
          ],
          "bio": {
            "experienceSummary": "My name is Marina I am a patient Pet Sitter. My outgoing demeanor and time management skills, along with my love of animals, make me uniquely qualified to care for pets of all kinds.",
            "title": null,
            "__typename": "Bio"
          },
          "id": "32170687",
          "numberOfPetsComfortableWith": 0,
          "otherQualities": [],
          "payRange": {
            "hourlyRateFrom": {
              "amount": "16",
              "currencyCode": "USD",
              "__typename": "Money"
            },
            "hourlyRateTo": {
              "amount": "20",
              "currencyCode": "USD",
              "__typename": "Money"
            },
            "__typename": "PayRange"
          },
          "petSpecies": {
            "caresForAmphibians": false,
            "caresForBirds": false,
            "caresForCats": true,
            "caresForDogs": true,
            "caresForExoticPets": false,
            "caresForFarmAnimals": false,
            "caresForFish": false,
            "caresForHorses": false,
            "caresForMammals": false,
            "caresForOtherPets": false,
            "__typename": "PetCareSpeciesCaredFor"
          },
          "qualities": {
            "isBondedAndInsured": true,
            "isNappsCertified": false,
            "isPSAMemberAndIsInsured": false,
            "isRedCrossPetFirstAidCertified": false,
            "doesNotSmoke": true,
            "ownsTransportation": false,
            "isCertifiedAndInsured": false,
            "isExperiencedWithChallengingPets": false,
            "isExperiencedWithSeniorPets": false,
            "isExperiencedWithSpecialNeedsPets": false,
            "isExperiencedWithYoungPets": false,
            "__typename": "PetCareQualities"
          },
          "recurringRate": {
            "hourlyRateFrom": {
              "currencyCode": "USD",
              "amount": "16",
              "__typename": "Money"
            },
            "hourlyRateTo": {
              "currencyCode": "USD",
              "amount": "20",
              "__typename": "Money"
            },
            "__typename": "PayRange"
          },
          "serviceRates": [
            {
              "rate": {
                "amount": "45",
                "currencyCode": "USD",
                "__typename": "Money"
              },
              "duration": "OVER_NIGHT",
              "subtype": "SITTING",
              "__typename": "PetCareSubtypeRate"
            },
            {
              "rate": {
                "amount": "41",
                "currencyCode": "USD",
                "__typename": "Money"
              },
              "duration": "OVER_NIGHT",
              "subtype": "BOARDING",
              "__typename": "PetCareSubtypeRate"
            },
            {
              "rate": {
                "amount": "41",
                "currencyCode": "USD",
                "__typename": "Money"
              },
              "duration": "PER_DAY",
              "subtype": "DAYCARE",
              "__typename": "PetCareSubtypeRate"
            },
            {
              "rate": {
                "amount": "18",
                "currencyCode": "USD",
                "__typename": "Money"
              },
              "duration": "PER_30_MIN",
              "subtype": "WALKING",
              "__typename": "PetCareSubtypeRate"
            },
            {
              "rate": {
                "amount": "28",
                "currencyCode": "USD",
                "__typename": "Money"
              },
              "duration": "PER_HOUR",
              "subtype": "WALKING",
              "__typename": "PetCareSubtypeRate"
            }
          ],
          "supportedServices": {
            "administersMedicine": false,
            "boardsOvernight": true,
            "doesDailyFeeding": false,
            "doesHouseSitting": false,
            "doesPetDaycare": false,
            "doesPetSitting": true,
            "doesPetWalking": true,
            "groomsAnimals": false,
            "retrievesMail": false,
            "trainsDogs": false,
            "transportsPets": false,
            "watersPlants": false,
            "__typename": "PetCareServices"
          },
          "yearsOfExperience": 1,
          "__typename": "PetCareCaregiverProfile"
        },
        "seniorCareCaregiverProfile": null,
        "tutoringCaregiverProfile": null,
        "houseKeepingCaregiverProfile": null,
        "__typename": "CaregiverProfiles"
      },
      "providerStatus": "ACTIVE",
      "recurringAvailability": {
        "dayList": {
          "monday": {
            "blocks": [
              {
                "end": "00:00:00",
                "start": "07:00:00",
                "__typename": "LocalTimeBlock"
              }
            ],
            "__typename": "DailySchedule"
          },
          "tuesday": {
            "blocks": [
              {
                "end": "00:00:00",
                "start": "07:00:00",
                "__typename": "LocalTimeBlock"
              }
            ],
            "__typename": "DailySchedule"
          },
          "wednesday": {
            "blocks": [
              {
                "end": "00:00:00",
                "start": "07:00:00",
                "__typename": "LocalTimeBlock"
              }
            ],
            "__typename": "DailySchedule"
          },
          "thursday": {
            "blocks": [
              {
                "end": "00:00:00",
                "start": "07:00:00",
                "__typename": "LocalTimeBlock"
              }
            ],
            "__typename": "DailySchedule"
          },
          "friday": {
            "blocks": [
              {
                "end": "00:00:00",
                "start": "07:00:00",
                "__typename": "LocalTimeBlock"
              }
            ],
            "__typename": "DailySchedule"
          },
          "saturday": {
            "blocks": [
              {
                "end": "00:00:00",
                "start": "07:00:00",
                "__typename": "LocalTimeBlock"
              }
            ],
            "__typename": "DailySchedule"
          },
          "sunday": {
            "blocks": [
              {
                "end": "00:00:00",
                "start": "07:00:00",
                "__typename": "LocalTimeBlock"
              }
            ],
            "__typename": "DailySchedule"
          },
          "__typename": "WeeklySchedule"
        },
        "__typename": "RecurringAvailability"
      },
      "responseRate": 79,
      "responseTime": 16,
      "signUpDate": "2022-01-31T22:41:00.000Z",
      "yearsOfExperience": 3,
      "nonPrimaryImages": [],
      "__typename": "Caregiver"
    }
  }
}