{
  "data": {
    "getCaregiver": {
      "continuousBackgroundCheck": {
        "seeker": {
          "hasLimitReached": false,
          "subscriptionStatus": null,
          "__typename": "SeekerContinuousBgcSubscriptionDto"
        },
        "hasActiveHit": false,
        "__typename": "ContinuousBackgroundCheck"
      },
      "backgroundChecks": [
        {
          "backgroundCheckName": "CARE_CHECK",
          "whenCompleted": "2024-09-06T09:42:00.000Z",
          "__typename": "BackgroundCheck"
        }
      ],
      "badges": [
        "BACKGROUND_CHECK",
        "VACCINATED"
      ],
      "distanceFromSeekerInMiles": null,
      "educationDegrees": [
        {
          "currentlyAttending": false,
          "degreeYear": null,
          "educationLevel": "COLLEGE_DEGREE",
          "schoolName": "Waterford High School",
          "educationDetailsText": [
            "Waterford High School",
            "College degree"
          ],
          "__typename": "EducationDegree"
        }
      ],
      "hasCareCheck": true,
      "hasGrantedCriminalBGCAccess": false,
      "hasGrantedMvrBGCAccess": false,
      "hasGrantedPremierBGCAccess": false,
      "hiredByCounts": {
        "locality": null,
        "__typename": "CaregiverHiredByCounts"
      },
      "hiredTimes": 0,
      "isFavorite": false,
      "isMVREligible": true,
      "isVaccinated": true,
      "member": {
        "id": "912feb59-596e-41bd-be9c-7ea7fefbcac0",
        "lastName": "C",
        "firstName": "Charles",
        "gender": "MALE",
        "hiResImageURL": "https://www.care.com/s/d/aws/photo/1080X1080/62/46499262_Mry46aeKCs9KRr5jeQqkOK9gIZ0vl00",
        "displayName": "Charles C.",
        "email": "frihaouiayoube@gmail.com",
        "primaryService": "HOUSEKEEPING",
        "imageURL": "https://www.care.com/s/d/aws/photo/135X135/62/46499262_Mry46aeKCs9KRr5jeQqkOK9gIZ0vl00",
        "address": {
          "city": "Bronx",
          "state": "NY",
          "zip": "10456",
          "__typename": "Address"
        },
        "languages": [
          "ENGLISH"
        ],
        "legacyId": "33237878",
        "isPremium": false,
        "__typename": "Member"
      },
      "placeInfo": null,
      "profiles": {
        "serviceIds": [
          "HOUSEKEEPING",
          "SENIOR_CARE"
        ],
        "childCareCaregiverProfile": null,
        "commonCaregiverProfile": {
          "id": "",
          "repeatClientsCount": 0,
          "merchandizedJobInterests": {
            "companionCare": false,
            "dateNight": false,
            "lightCleaning": true,
            "mealPrepLaundry": false,
            "mover": true,
            "personalAssistant": true,
            "petHelp": false,
            "shopping": false,
            "transportation": false,
            "__typename": "MerchandizedJobInterests"
          },
          "__typename": "CommonCaregiverProfile"
        },
        "petCareCaregiverProfile": null,
        "seniorCareCaregiverProfile": {
          "approvalStatus": "INACTIVE",
          "availabilityFrequency": "PART_TIME",
          "bio": {
            "experienceSummary": "I give my clients supporting services including daily activities like letter writing, paying bills, collecting benefits.",
            "title": null,
            "__typename": "Bio"
          },
          "id": "35253385",
          "otherQualities": [],
          "payRange": {
            "hourlyRateFrom": {
              "amount": "17",
              "currencyCode": "USD",
              "__typename": "Money"
            },
            "hourlyRateTo": {
              "amount": "21",
              "currencyCode": "USD",
              "__typename": "Money"
            },
            "__typename": "PayRange"
          },
          "qualities": {
            "alzheimersOrDementiaExperience": false,
            "certifiedNursingAssistant": false,
            "comfortableWithPets": true,
            "cprTrained": false,
            "doesNotSmoke": true,
            "firstAidTraining": false,
            "homeHealthAideExperience": false,
            "hospiceExperience": false,
            "licensedNurse": false,
            "medicalEquipmentExperience": false,
            "ownTransportation": false,
            "registeredNurse": false,
            "woundCare": false,
            "__typename": "SeniorCareCaregiverQualities"
          },
          "recurringRate": {
            "hourlyRateFrom": {
              "currencyCode": "USD",
              "amount": "17",
              "__typename": "Money"
            },
            "hourlyRateTo": {
              "currencyCode": "USD",
              "amount": "21",
              "__typename": "Money"
            },
            "__typename": "PayRange"
          },
          "supportedServices": {
            "visitingPhysician": false,
            "visitingNurse": false,
            "transportation": false,
            "specializedCare": false,
            "specialNeeds": false,
            "respiteCare": false,
            "personalCare": false,
            "mobilityAssistance": false,
            "medicalTransportation": false,
            "medicalManagement": false,
            "mealPreparation": false,
            "lightHousekeeping": true,
            "liveInHomeCare": false,
            "hospiceServices": false,
            "homeModification": false,
            "homeHealth": false,
            "helpStayingPhysicallyActive": false,
            "heavyLifting": false,
            "feeding": false,
            "errands": false,
            "dementia": false,
            "companionship": false,
            "bathing": false,
            "__typename": "SeniorCareCaregiverServices"
          },
          "yearsOfExperience": 3,
          "__typename": "SeniorCareCaregiverProfile"
        },
        "tutoringCaregiverProfile": null,
        "houseKeepingCaregiverProfile": {
          "approvalStatus": "APPROVED",
          "availabilityFrequency": "PART_TIME",
          "bio": {
            "experienceSummary": "Trained professional cleaner providing you with best cleaning services. Your Home is Safe with Me! Reliable Worker, Hardworking and Responsible! Immediate Availability - Flexible Hours.",
            "title": null,
            "__typename": "Bio"
          },
          "distanceWillingToTravel": null,
          "id": "20461557",
          "otherQualities": [],
          "payRange": {
            "hourlyRateFrom": {
              "amount": "19",
              "currencyCode": "USD",
              "__typename": "Money"
            },
            "hourlyRateTo": {
              "amount": "19",
              "currencyCode": "USD",
              "__typename": "Money"
            },
            "__typename": "PayRange"
          },
          "qualities": {
            "comfortableWithPets": true,
            "doesNotSmoke": true,
            "ownTransportation": false,
            "providesEquipment": true,
            "providesSupplies": true,
            "__typename": "HousekeeperQualities"
          },
          "recurringRate": {
            "hourlyRateFrom": {
              "amount": "19",
              "currencyCode": "USD",
              "__typename": "Money"
            },
            "hourlyRateTo": {
              "amount": "19",
              "currencyCode": "USD",
              "__typename": "Money"
            },
            "__typename": "PayRange"
          },
          "schedule": [],
          "supportedServices": {
            "atticCleaning": true,
            "basementCleaning": true,
            "bathroomCleaning": true,
            "cabinetCleaning": true,
            "carpetCleaning": true,
            "changingBedLinens": true,
            "deepCleaning": false,
            "dishes": false,
            "dusting": false,
            "furnitureTreatment": false,
            "generalRoomCleaning": true,
            "houseSitting": false,
            "kitchenCleaning": true,
            "laundry": false,
            "moveOutCleaning": false,
            "organization": false,
            "ovenCleaning": true,
            "packingUnpacking": false,
            "petWasteCleanup": true,
            "plantCare": false,
            "refrigeratorCleaning": true,
            "standardCleaning": false,
            "surfacePolishing": false,
            "vacuumingOrMopping": false,
            "wallWashing": true,
            "windowWashing": true,
            "__typename": "HousekeeperServices"
          },
          "yearsOfExperience": 10,
          "__typename": "HouseKeepingCaregiverProfile"
        },
        "__typename": "CaregiverProfiles"
      },
      "providerStatus": "ACTIVE",
      "recurringAvailability": {
        "dayList": {
          "monday": {
            "blocks": [
              {
                "end": "17:00:00",
                "start": "09:00:00",
                "__typename": "LocalTimeBlock"
              }
            ],
            "__typename": "DailySchedule"
          },
          "tuesday": {
            "blocks": [
              {
                "end": "17:00:00",
                "start": "09:00:00",
                "__typename": "LocalTimeBlock"
              }
            ],
            "__typename": "DailySchedule"
          },
          "wednesday": {
            "blocks": [
              {
                "end": "17:00:00",
                "start": "09:00:00",
                "__typename": "LocalTimeBlock"
              }
            ],
            "__typename": "DailySchedule"
          },
          "thursday": {
            "blocks": [
              {
                "end": "17:00:00",
                "start": "09:00:00",
                "__typename": "LocalTimeBlock"
              }
            ],
            "__typename": "DailySchedule"
          },
          "friday": {
            "blocks": [
              {
                "end": "17:00:00",
                "start": "09:00:00",
                "__typename": "LocalTimeBlock"
              }
            ],
            "__typename": "DailySchedule"
          },
          "saturday": {
            "blocks": [
              {
                "end": "17:00:00",
                "start": "10:00:00",
                "__typename": "LocalTimeBlock"
              }
            ],
            "__typename": "DailySchedule"
          },
          "sunday": {
            "blocks": [
              {
                "end": "15:00:00",
                "start": "00:00:00",
                "__typename": "LocalTimeBlock"
              }
            ],
            "__typename": "DailySchedule"
          },
          "__typename": "WeeklySchedule"
        },
        "__typename": "RecurringAvailability"
      },
      "responseRate": 0,
      "responseTime": 0,
      "signUpDate": "2017-11-30T12:20:00.000Z",
      "yearsOfExperience": 0,
      "nonPrimaryImages": [
        "https://www.care.com/s/d/aws/photo/1080X1080/35/46499535_Mry46aeKCs9KRr5jeQqkOK9gIZ0vl00",
        "https://www.care.com/s/d/aws/photo/1080X1080/42/46499542_Mry46aeKCs9KRr5jeQqkOK9gIZ0vl00",
        "https://www.care.com/s/d/aws/photo/1080X1080/12/46524312_Mry46aeKCs9KRr5jeQqkOK9gIZ0vl00",
        "https://www.care.com/s/d/aws/photo/1080X1080/52/46571352_Mry46aeKCs9KRr5jeQqkOK9gIZ0vl00",
        "https://www.care.com/s/d/aws/photo/1080X1080/56/46571356_Mry46aeKCs9KRr5jeQqkOK9gIZ0vl00"
      ],
      "__typename": "Caregiver"
    }
  }
}