{
  "data": {
    "reviewsByReviewee": {
      "__typename": "ReviewsByRevieweePayload",
      "nextPageToken": "",
      "reviews": [
        {
          "attributes": [
            {
              "truthy": true,
              "type": "HIRED",
              "__typename": "ReviewInfoAttribute"
            },
            {
              "truthy": true,
              "type": "REHIRED",
              "__typename": "ReviewInfoAttribute"
            },
            {
              "truthy": false,
              "type": "SAFETY_CONCERN",
              "__typename": "ReviewInfoAttribute"
            }
          ],
          "careType": "SENIOR_CARE",
          "createTime": "2024-09-13T15:20:50.162Z",
          "deleteTime": null,
          "description": {
            "displayText": "",
            "originalText": "Natia took care of my elderly mom who has dementia.  Natia consistently treated my mom with kindness and compassion.  Natia tended to my mom's needs with patience and competence and my mom developed a very sweet bond with Natia.  There wasn't any problem Natia couldn't solve.  Natia is very honest and reliable, and provided some much-needed relief to my family.   ",
            "__typename": "ReviewInfoText"
          },
          "id": "30896b4e-32d4-5b21-8e01-67ede0d9ffd0",
          "languageCode": "en-us",
          "originalSource": "MFE",
          "ratings": [
            {
              "type": "OVERALL",
              "value": 5,
              "__typename": "ReviewInfoRating"
            }
          ],
          "retort": null,
          "reviewee": {
            "id": "5f705d07-7bc2-4137-9774-76e91f8336f5",
            "providerType": "COMPANY",
            "type": "PROVIDER",
            "__typename": "ReviewInfoReviewee"
          },
          "reviewer": {
            "imageURL": null,
            "publicMemberInfo": {
              "firstName": "Alise",
              "lastInitial": "B",
              "__typename": "PublicMemberInfo"
            },
            "source": "CZEN",
            "type": "PROVIDER",
            "__typename": "ReviewInfoReviewer"
          },
          "status": "APPROVED",
          "updateSource": null,
          "updateTime": "2024-09-13T15:20:51.084Z",
          "verifiedByCare": false,
          "__typename": "ReviewInfo"
        },
        {
          "attributes": [
            {
              "truthy": true,
              "type": "HIRED",
              "__typename": "ReviewInfoAttribute"
            },
            {
              "truthy": true,
              "type": "REHIRED",
              "__typename": "ReviewInfoAttribute"
            },
            {
              "truthy": false,
              "type": "SAFETY_CONCERN",
              "__typename": "ReviewInfoAttribute"
            }
          ],
          "careType": "SENIOR_CARE",
          "createTime": "2024-09-08T16:23:37.842Z",
          "deleteTime": null,
          "description": {
            "displayText": "",
            "originalText": "We had the pleasure of working with Natia temporarily after my mother's operation. Although her time with us was short, she made a significant impact. Natia was extremely professional, attentive, and compassionate throughout her stay. She provided excellent care, ensuring my mother was comfortable and well taken care of during her recovery period.\n\nHer warm personality and willingness to assist with any task made a difficult time much more manageable. Even though her role was temporary, Natia felt like an essential part of our family",
            "__typename": "ReviewInfoText"
          },
          "id": "493f568c-0305-557c-b92f-a489a2b22784",
          "languageCode": "en-us",
          "originalSource": "MFE",
          "ratings": [
            {
              "type": "OVERALL",
              "value": 5,
              "__typename": "ReviewInfoRating"
            }
          ],
          "retort": null,
          "reviewee": {
            "id": "5f705d07-7bc2-4137-9774-76e91f8336f5",
            "providerType": "COMPANY",
            "type": "PROVIDER",
            "__typename": "ReviewInfoReviewee"
          },
          "reviewer": {
            "imageURL": null,
            "publicMemberInfo": {
              "firstName": "Jennifer",
              "lastInitial": "M",
              "__typename": "PublicMemberInfo"
            },
            "source": "CZEN",
            "type": "PROVIDER",
            "__typename": "ReviewInfoReviewer"
          },
          "status": "APPROVED",
          "updateSource": null,
          "updateTime": "2024-09-08T16:23:38.547Z",
          "verifiedByCare": false,
          "__typename": "ReviewInfo"
        },
        {
          "attributes": [
            {
              "truthy": true,
              "type": "HIRED",
              "__typename": "ReviewInfoAttribute"
            },
            {
              "truthy": true,
              "type": "REHIRED",
              "__typename": "ReviewInfoAttribute"
            }
          ],
          "careType": "SENIOR_CARE",
          "createTime": "2024-04-24T01:56:16.095Z",
          "deleteTime": null,
          "description": {
            "displayText": "",
            "originalText": "Natia cared for my mother in law for over two years.  We believe that my mother in law and our whole family, was truly blessed to have had such competent and tender care.\n Natia is patient, good natured, honest, caring, respectful and encouraging.  She is also very knowledgeable about the various needs of people who need help, and of various kinds of assistance that are helpful in differing situations.\nWe also appreciated Natia’s willingness and openness in communicating with us, as we lived at some distance from our mother. \nWe recommend Natia wholeheartedly and without any hesitation to whomever would be fortunate to be able to consider having her care for themselves or a loved one.",
            "__typename": "ReviewInfoText"
          },
          "id": "07656e4b-1a10-4b50-8644-cd92d1d38ef5",
          "languageCode": "en-us",
          "originalSource": "MFE",
          "ratings": [
            {
              "type": "OVERALL",
              "value": 5,
              "__typename": "ReviewInfoRating"
            }
          ],
          "retort": null,
          "reviewee": {
            "id": "5f705d07-7bc2-4137-9774-76e91f8336f5",
            "providerType": "INDIVIDUAL",
            "type": "PROVIDER",
            "__typename": "ReviewInfoReviewee"
          },
          "reviewer": {
            "imageURL": null,
            "publicMemberInfo": {
              "firstName": "Ia",
              "lastInitial": "S",
              "__typename": "PublicMemberInfo"
            },
            "source": "CZEN",
            "type": "SEEKER",
            "__typename": "ReviewInfoReviewer"
          },
          "status": "APPROVED",
          "updateSource": null,
          "updateTime": "2024-04-24T01:56:17.285Z",
          "verifiedByCare": false,
          "__typename": "ReviewInfo"
        },
        {
          "attributes": [
            {
              "truthy": true,
              "type": "HIRED",
              "__typename": "ReviewInfoAttribute"
            },
            {
              "truthy": true,
              "type": "REHIRED",
              "__typename": "ReviewInfoAttribute"
            },
            {
              "truthy": false,
              "type": "SAFETY_CONCERN",
              "__typename": "ReviewInfoAttribute"
            }
          ],
          "careType": "SENIOR_CARE",
          "createTime": "2024-04-22T10:02:03.522Z",
          "deleteTime": null,
          "description": {
            "displayText": "",
            "originalText": "It whom it may concern,\nDuring the two months I have known Natia as a care giver for my mom. I have witnessed her display exceptional compassion.\nFor example. Natia's compassion made it possible for us to know that my mother was in good hands and cared for every minute of the day. She cooked, cleaned and was a wonderful companion for my mom.\nI am confident that Natia's attitude and skills would make her a valuable contributor to any household. Please do not hesitate to contact me with any additional questions you may have.\n",
            "__typename": "ReviewInfoText"
          },
          "id": "9a55d440-4709-493e-9ccd-5771a502c3bc",
          "languageCode": "en-us",
          "originalSource": "MFE",
          "ratings": [
            {
              "type": "OVERALL",
              "value": 5,
              "__typename": "ReviewInfoRating"
            }
          ],
          "retort": null,
          "reviewee": {
            "id": "5f705d07-7bc2-4137-9774-76e91f8336f5",
            "providerType": "COMPANY",
            "type": "PROVIDER",
            "__typename": "ReviewInfoReviewee"
          },
          "reviewer": {
            "imageURL": null,
            "publicMemberInfo": {
              "firstName": "James",
              "lastInitial": "B",
              "__typename": "PublicMemberInfo"
            },
            "source": "CZEN",
            "type": "PROVIDER",
            "__typename": "ReviewInfoReviewer"
          },
          "status": "APPROVED",
          "updateSource": null,
          "updateTime": "2024-04-22T10:02:05.884Z",
          "verifiedByCare": false,
          "__typename": "ReviewInfo"
        },
        {
          "attributes": [
            {
              "truthy": true,
              "type": "HIRED",
              "__typename": "ReviewInfoAttribute"
            },
            {
              "truthy": true,
              "type": "REHIRED",
              "__typename": "ReviewInfoAttribute"
            },
            {
              "truthy": false,
              "type": "SAFETY_CONCERN",
              "__typename": "ReviewInfoAttribute"
            }
          ],
          "careType": "SENIOR_CARE",
          "createTime": "2024-04-17T18:08:52.470Z",
          "deleteTime": null,
          "description": {
            "displayText": "",
            "originalText": "If you are looking for a reliable, compassionate caregiver who has your loved one’s best interests at heart, then you need Natia! During the time that she cared for our mother, Natia became like one of the family. Her presence allowed our mom to spend her final months in her own home, feeling comfortable and safe. Natia’s stamina and skill at addressing personal needs as well as assisting in activities of daily living is impressive, and matched only by her patience and empathy. She communicated with our mother almost intuitively, and was always kind and mindful in relation to Mom’s cognitive decline. She is worth her weight in gold.",
            "__typename": "ReviewInfoText"
          },
          "id": "884adf03-5cf0-4407-a8ea-d1e1bf18743f",
          "languageCode": "en-us",
          "originalSource": "MFE",
          "ratings": [
            {
              "type": "OVERALL",
              "value": 5,
              "__typename": "ReviewInfoRating"
            }
          ],
          "retort": null,
          "reviewee": {
            "id": "5f705d07-7bc2-4137-9774-76e91f8336f5",
            "providerType": "COMPANY",
            "type": "PROVIDER",
            "__typename": "ReviewInfoReviewee"
          },
          "reviewer": {
            "imageURL": null,
            "publicMemberInfo": {
              "firstName": "Emily",
              "lastInitial": "S",
              "__typename": "PublicMemberInfo"
            },
            "source": "CZEN",
            "type": "PROVIDER",
            "__typename": "ReviewInfoReviewer"
          },
          "status": "APPROVED",
          "updateSource": null,
          "updateTime": "2024-04-17T18:08:53.380Z",
          "verifiedByCare": false,
          "__typename": "ReviewInfo"
        },
        {
          "attributes": [
            {
              "truthy": true,
              "type": "HIRED",
              "__typename": "ReviewInfoAttribute"
            },
            {
              "truthy": true,
              "type": "REHIRED",
              "__typename": "ReviewInfoAttribute"
            },
            {
              "truthy": false,
              "type": "SAFETY_CONCERN",
              "__typename": "ReviewInfoAttribute"
            }
          ],
          "careType": "SENIOR_CARE",
          "createTime": "2024-04-17T16:21:03.798Z",
          "deleteTime": null,
          "description": {
            "displayText": "",
            "originalText": "It is my privilege to recommend Natia to you as a caregiver for your aging mother. Natia took wonderful care of my mother. She is extremely compassionate and completely trustworthy. While caring for my mother Natia performed a variety of daily activities. She assisted my mother with bathing, dressing, preparing and feeding meals and administering medications. She took my mother for walks around the neighborhoodevery day, weather permitting, to allow her to get fresh air regularly. Natia drove my mother to routine physician appointments and checkups. She took care of the laundry as well as changing bed linens. Natia was a wonderful companion for my mother, and she spent time in conversation with her to help keep her mind as sharp as possible.\nI hope that you will seriously consider Natia for the position as your mother’s caregiver. I am confident that you will be as happy with her work as we were.",
            "__typename": "ReviewInfoText"
          },
          "id": "11642ad5-6337-4809-a076-b159f569101d",
          "languageCode": "en-us",
          "originalSource": "MFE",
          "ratings": [
            {
              "type": "OVERALL",
              "value": 5,
              "__typename": "ReviewInfoRating"
            }
          ],
          "retort": null,
          "reviewee": {
            "id": "5f705d07-7bc2-4137-9774-76e91f8336f5",
            "providerType": "COMPANY",
            "type": "PROVIDER",
            "__typename": "ReviewInfoReviewee"
          },
          "reviewer": {
            "imageURL": null,
            "publicMemberInfo": {
              "firstName": "Jennifer",
              "lastInitial": "W",
              "__typename": "PublicMemberInfo"
            },
            "source": "CZEN",
            "type": "PROVIDER",
            "__typename": "ReviewInfoReviewer"
          },
          "status": "APPROVED",
          "updateSource": null,
          "updateTime": "2024-04-17T16:21:06.331Z",
          "verifiedByCare": false,
          "__typename": "ReviewInfo"
        },
        {
          "attributes": [
            {
              "truthy": true,
              "type": "HIRED",
              "__typename": "ReviewInfoAttribute"
            },
            {
              "truthy": true,
              "type": "REHIRED",
              "__typename": "ReviewInfoAttribute"
            },
            {
              "truthy": false,
              "type": "SAFETY_CONCERN",
              "__typename": "ReviewInfoAttribute"
            }
          ],
          "careType": "SENIOR_CARE",
          "createTime": "2024-04-04T18:33:18.840Z",
          "deleteTime": null,
          "description": {
            "displayText": "",
            "originalText": "I recommend Natia with great pleasure and gratitude, she helped my close friend recently for several months, who was unable to do self care for a while and do housework. She is educated, nice and trustworthy caregiver , highly recommend her service.",
            "__typename": "ReviewInfoText"
          },
          "id": "730e1f64-6a2b-44fc-9818-8f35dbaeebe2",
          "languageCode": "en-us",
          "originalSource": "MFE",
          "ratings": [
            {
              "type": "OVERALL",
              "value": 5,
              "__typename": "ReviewInfoRating"
            }
          ],
          "retort": null,
          "reviewee": {
            "id": "5f705d07-7bc2-4137-9774-76e91f8336f5",
            "providerType": "COMPANY",
            "type": "PROVIDER",
            "__typename": "ReviewInfoReviewee"
          },
          "reviewer": {
            "imageURL": null,
            "publicMemberInfo": {
              "firstName": "Natia",
              "lastInitial": "T",
              "__typename": "PublicMemberInfo"
            },
            "source": "CZEN",
            "type": "PROVIDER",
            "__typename": "ReviewInfoReviewer"
          },
          "status": "APPROVED",
          "updateSource": null,
          "updateTime": "2024-04-04T18:33:20.134Z",
          "verifiedByCare": false,
          "__typename": "ReviewInfo"
        },
        {
          "attributes": [
            {
              "truthy": true,
              "type": "HIRED",
              "__typename": "ReviewInfoAttribute"
            },
            {
              "truthy": true,
              "type": "REHIRED",
              "__typename": "ReviewInfoAttribute"
            },
            {
              "truthy": false,
              "type": "SAFETY_CONCERN",
              "__typename": "ReviewInfoAttribute"
            }
          ],
          "careType": "SENIOR_CARE",
          "createTime": "2024-04-04T18:27:07.022Z",
          "deleteTime": null,
          "description": {
            "displayText": "I know Mrs. Natia G. since 2019, I am very satisfied with her morality and probity. Highly recommended ",
            "originalText": "I know Mrs. Natia G. since 2019, I am very satisfied with her morality and probity. Highly recommended ",
            "__typename": "ReviewInfoText"
          },
          "id": "ae24ca76-0925-4492-99d3-71c2e934bfe8",
          "languageCode": "en-us",
          "originalSource": "MFE",
          "ratings": [
            {
              "type": "OVERALL",
              "value": 5,
              "__typename": "ReviewInfoRating"
            }
          ],
          "retort": null,
          "reviewee": {
            "id": "5f705d07-7bc2-4137-9774-76e91f8336f5",
            "providerType": "COMPANY",
            "type": "PROVIDER",
            "__typename": "ReviewInfoReviewee"
          },
          "reviewer": {
            "imageURL": null,
            "publicMemberInfo": {
              "firstName": "Inga",
              "lastInitial": "F",
              "__typename": "PublicMemberInfo"
            },
            "source": "CZEN",
            "type": "PROVIDER",
            "__typename": "ReviewInfoReviewer"
          },
          "status": "APPROVED",
          "updateSource": "EMPLOYEE",
          "updateTime": "2024-04-05T11:17:05.675Z",
          "verifiedByCare": false,
          "__typename": "ReviewInfo"
        },
        {
          "attributes": [
            {
              "truthy": true,
              "type": "HIRED",
              "__typename": "ReviewInfoAttribute"
            },
            {
              "truthy": true,
              "type": "REHIRED",
              "__typename": "ReviewInfoAttribute"
            },
            {
              "truthy": false,
              "type": "SAFETY_CONCERN",
              "__typename": "ReviewInfoAttribute"
            }
          ],
          "careType": "SENIOR_CARE",
          "createTime": "2024-04-04T18:26:40.540Z",
          "deleteTime": null,
          "description": {
            "displayText": "",
            "originalText": "SHe did a great job with my aunt, thanks ",
            "__typename": "ReviewInfoText"
          },
          "id": "832eb92d-5ecf-44b4-8cde-5d0e4da97b5a",
          "languageCode": "en-us",
          "originalSource": "MFE",
          "ratings": [
            {
              "type": "OVERALL",
              "value": 5,
              "__typename": "ReviewInfoRating"
            }
          ],
          "retort": null,
          "reviewee": {
            "id": "5f705d07-7bc2-4137-9774-76e91f8336f5",
            "providerType": "COMPANY",
            "type": "PROVIDER",
            "__typename": "ReviewInfoReviewee"
          },
          "reviewer": {
            "imageURL": null,
            "publicMemberInfo": {
              "firstName": "Megi",
              "lastInitial": "M",
              "__typename": "PublicMemberInfo"
            },
            "source": "CZEN",
            "type": "PROVIDER",
            "__typename": "ReviewInfoReviewer"
          },
          "status": "APPROVED",
          "updateSource": null,
          "updateTime": "2024-04-04T18:26:41.751Z",
          "verifiedByCare": false,
          "__typename": "ReviewInfo"
        }
      ]
    }
  }
}