{
  "data": {
    "reviewsByReviewee": {
      "__typename": "ReviewsByRevieweePayload",
      "nextPageToken": "",
      "reviews": [
        {
          "attributes": [
            {
              "truthy": true,
              "type": "REHIRED",
              "__typename": "ReviewInfoAttribute"
            }
          ],
          "careType": "CHILD_CARE",
          "createTime": "2015-12-29T02:35:48.000Z",
          "deleteTime": null,
          "description": {
            "displayText": "Ashley was such a great babysitter!  She was always on time, always engaged with the children, and always so helpful.  We really trusted Ashley and never had any doubts about her abilities to keep the children safe and happy.",
            "originalText": "Ashley was such a great babysitter!  She was always on time, always engaged with the children, and always so helpful.  We really trusted Ashley and never had any doubts about her abilities to keep the children safe and happy.",
            "__typename": "ReviewInfoText"
          },
          "id": "74fab882-75ea-4502-93e1-64c803cd6281",
          "languageCode": "en-us",
          "originalSource": "CZEN",
          "ratings": [
            {
              "type": "OVERALL",
              "value": 5,
              "__typename": "ReviewInfoRating"
            },
            {
              "type": "DEPENDABILITY",
              "value": 5,
              "__typename": "ReviewInfoRating"
            },
            {
              "type": "PUNCTUALITY",
              "value": 5,
              "__typename": "ReviewInfoRating"
            },
            {
              "type": "RELIABLE_TRANSPORTATION",
              "value": 5,
              "__typename": "ReviewInfoRating"
            }
          ],
          "retort": null,
          "reviewee": {
            "id": "dc4b73d2-de02-401d-ade4-09ff5d04c0c6",
            "providerType": "INDIVIDUAL",
            "type": "PROVIDER",
            "__typename": "ReviewInfoReviewee"
          },
          "reviewer": {
            "imageURL": null,
            "publicMemberInfo": {
              "firstName": "Megan",
              "lastInitial": "P",
              "__typename": "PublicMemberInfo"
            },
            "source": "CZEN",
            "type": "SEEKER",
            "__typename": "ReviewInfoReviewer"
          },
          "status": "APPROVED",
          "updateSource": "CZEN",
          "updateTime": "2016-12-21T09:34:50.000Z",
          "verifiedByCare": false,
          "__typename": "ReviewInfo"
        }
      ]
    }
  }
}